mcdecoder/__init__.py
mcdecoder/__main__.py
mcdecoder/__version__.py
mcdecoder/app.py
mcdecoder/checker.py
mcdecoder/common.py
mcdecoder/core.py
mcdecoder/emulator.py
mcdecoder/exporter.py
mcdecoder/generator.py
mcdecoder/py.typed
mcdecoder/grammars/__init__.py
mcdecoder/grammars/instruction_condition.lark
mcdecoder/grammars/instruction_encoding.lark
mcdecoder/schemas/__init__.py
mcdecoder/schemas/mc_desc_schema.json
mcdecoder/templates/athrill/{{ns}}mcdecoder.c
mcdecoder/templates/athrill/{{ns}}mcdecoder.h
mcdecoder/templates/c_decoder/{{ns}}mcdecoder.c
mcdecoder/templates/c_decoder/{{ns}}mcdecoder.h
mcdecoder-0.1.1.dist-info/LICENSE
mcdecoder-0.1.1.dist-info/METADATA
mcdecoder-0.1.1.dist-info/WHEEL
mcdecoder-0.1.1.dist-info/entry_points.txt
mcdecoder-0.1.1.dist-info/top_level.txt
mcdecoder-0.1.1.dist-info/RECORD
