Metadata-Version: 2.1
Name: mcdecoder
Version: 0.1.1
Summary: The generator of a machine code decoder, transforming a user-defined machine code specification into decoder codes.
Home-page: https://github.com/wildlarva/mcdecoder
Author: wildlarva
Project-URL: Documentation, https://wildlarva.github.io/mcdecoder/
Classifier: Programming Language :: Python :: 3.8
Classifier: Operating System :: OS Independent
Classifier: Environment :: Console
Classifier: License :: OSI Approved :: MIT License
Classifier: Intended Audience :: Developers
Classifier: Topic :: Software Development :: Code Generators
Classifier: Programming Language :: C
Classifier: Development Status :: 4 - Beta
Requires-Python: >=3.8
License-File: LICENSE
Requires-Dist: deprecation >=2.0.7
Requires-Dist: Jinja2 >=3.1.3
Requires-Dist: jsonschema >=3.2.0
Requires-Dist: lark-parser >=0.9.0
Requires-Dist: numpy >=1.24.0
Requires-Dist: PyYAML >=6.0
